README.rst
setup.py
poom/__init__.py
poom/app.py
poom.egg-info/PKG-INFO
poom.egg-info/SOURCES.txt
poom.egg-info/dependency_links.txt
poom.egg-info/entry_points.txt
poom.egg-info/not-zip-safe
poom.egg-info/requires.txt
poom.egg-info/top_level.txt