Metadata-Version: 1.1
Name: poom
Version: 0.0.4
Summary: Open office documents with Microsoft Office Online
Home-page: http://redmoses.github.io/poom/
Author: redmoses
Author-email: musa@redmoses.me
License: MIT
Keywords: dropbox,microsoft office,office online
Platform: Linux
Classifier: Development Status :: 4 - Beta
Classifier: License :: OSI Approved :: MIT License
Classifier: Programming Language :: Python :: 2.7
Classifier: Topic :: Utilities
Classifier: Environment :: Console
Classifier: Natural Language :: English
Classifier: Operating System :: POSIX :: Linux
